mithermometer/__init__.py
mithermometer/mithermometer_poller.py
mithermometer/mithermometer_scanner.py
test/__init__.py
test/conftest.py
test/helper.py
test/integration_tests/__init__.py
test/integration_tests/test_bluepy_backend.py
test/integration_tests/test_demo.py
test/integration_tests/test_everything.py
test/integration_tests/test_gatttool_backend.py
test/integration_tests/test_pygatt_backend.py
test/no_imports/__init__.py
test/no_imports/test_noimports.py
test/unit_tests/__init__.py
test/unit_tests/test_mithermometer_poller.py
test/unit_tests/test_mithermometer_scanner.py
test/unit_tests/test_parse.py
test/unit_tests/test_versioncheck.py
mithermometer-0.1.4.dist-info/LICENSE
mithermometer-0.1.4.dist-info/METADATA
mithermometer-0.1.4.dist-info/WHEEL
mithermometer-0.1.4.dist-info/top_level.txt
mithermometer-0.1.4.dist-info/RECORD
