Metadata-Version: 2.1
Name: mithermometer
Version: 0.1.4
Summary: Library to read data from Xiaomi Aqara thermometer
Home-page: https://github.com/hobbypunk90/mithermometer
Author: Marcel Hoppe
Author-email: hoppe.marcel@gmail.com
License: MIT
Keywords: thermometer temperature humidity sensor bluetooth low-energy ble
Platform: UNKNOWN
Classifier: Development Status :: 5 - Production/Stable
Classifier: Intended Audience :: Developers
Classifier: Topic :: System :: Hardware :: Hardware Drivers
Classifier: License :: OSI Approved :: MIT License
Classifier: Programming Language :: Python :: 3
Classifier: Programming Language :: Python :: 3.4
Classifier: Programming Language :: Python :: 3.5
Requires-Dist: btlewrap (==0.0.9)
Provides-Extra: testing
Requires-Dist: pytest ; extra == 'testing'
